[
  {
    "title": "5TH EARTH",
    "price": "27,00 €",
    "link": "/proizvod/5th-earth"
  },
  {
    "title": "5TH WATER",
    "price": "27,00 €",
    "link": "/proizvod/5th-water"
  },
  {
    "title": "AKORI PREMIUM",
    "price": "32,00 €",
    "link": "/proizvod/akori-premium"
  },
  {
    "title": "AKORI YUZU",
    "price": "33,00 €",
    "link": "/proizvod/akori-yuzu"
  },
  {
    "title": "ALKKEMIST",
    "price": "47,00 €",
    "link": "/proizvod/alkkemist"
  },
  {
    "title": "AMAZZONI",
    "price": "38,00 €",
    "link": "/proizvod/amazzoni"
  },
  {
    "title": "AMAZZONI MANIUARA",
    "price": "39,00 €",
    "link": "/proizvod/amazzoni-maniuara"
  },
  {
    "title": "AMAZZONI RIO NEGRO",
    "price": "45,00 €",
    "link": "/proizvod/amazzoni-rio-negro"
  },
  {
    "title": "AMUERTE COCA LEAF - BLACK EDITION",
    "price": "71,00 €",
    "link": "/proizvod/amuerte-coca-leaf-black-edition"
  },
  {
    "title": "AMUERTE COCA LEAF - RED EDITION",
    "price": "75,00 €",
    "link": "/proizvod/amuerte-coca-leaf-red-edition"
  },
  {
    "title": "AMUERTE COCA LEAF - WHITE EDITION",
    "price": "69,00 €",
    "link": "/proizvod/amuerte-coca-leaf-white-edition"
  },
  {
    "title": "AMUERTE COCA LEAF GIN – BLUE EDITION",
    "price": "75,00 €",
    "link": "/proizvod/amuerte-coca-leaf-gin-blue-edition"
  },
  {
    "title": "AMUERTE COCA LEAF GIN – GREEN EDITION",
    "price": "75,00 €",
    "link": "/proizvod/amuerte-coca-leaf-gin-green-edition"
  },
  {
    "title": "AMUERTE COCA LEAF GIN – ORANGE EDITION",
    "price": "75,00 €",
    "link": "/proizvod/amuerte-coca-leaf-gin-orange-edition"
  },
  {
    "title": "AURA KARBUN",
    "price": "37,00 €",
    "link": "/proizvod/aura-karbun"
  },
  {
    "title": "AURA KARBUN NAVY STRENGHT",
    "price": "60,00 €",
    "link": "/proizvod/aura-karbun-navy-strenght"
  },
  {
    "title": "AVIATION",
    "price": "32,00 €",
    "link": "/proizvod/aviation"
  },
  {
    "title": "BATHTUB",
    "price": "37,00 €",
    "link": "/proizvod/bathtub"
  },
  {
    "title": "BEEFEATER",
    "price": "18,00 €",
    "link": "/proizvod/beefeater"
  },
  {
    "title": "BEEFEATER 24",
    "price": "29,00 €",
    "link": "/proizvod/beefeater-24"
  },
  {
    "title": "BEEFEATER BLOOD ORANGE",
    "price": "20,00 €",
    "link": "/proizvod/beefeater-blood-orange"
  },
  {
    "title": "BEEFEATER PINK",
    "price": "20,00 €",
    "link": "/proizvod/beefeater-pink"
  },
  {
    "title": "BLACK TOMATO",
    "price": "38,00 €",
    "link": "/proizvod/black-tomato"
  },
  {
    "title": "BLACKWOODS VINTAGE 2021 DRY GIN",
    "price": "27,00 €",
    "link": "/proizvod/blackwoods-vintage-2021-dry-gin"
  },
  {
    "title": "BLOSSOM GIN COSTA BLANCA",
    "price": "29,00 €",
    "link": "/proizvod/blossom-gin-costa-blanca"
  },
  {
    "title": "BLOSSOM GIN GRAN RESERVA",
    "price": "29,00 €",
    "link": "/proizvod/blossom-gin-gran-reserva"
  },
  {
    "title": "BLOSSOM GIN PEACH",
    "price": "28,00 €",
    "link": "/proizvod/blossom-gin-peach"
  },
  {
    "title": "BOMBAY ORIGINAL",
    "price": "18,00 €",
    "link": "/proizvod/bombay-original"
  },
  {
    "title": "BOMBAY SAPPHIRE",
    "price": "21,00 €",
    "link": "/proizvod/bombay-sapphire"
  },
  {
    "title": "BOMBAY SAPPHIRE EAST",
    "price": "29,00 €",
    "link": "/proizvod/bombay-sapphire-east"
  },
  {
    "title": "BOODLES",
    "price": "25,00 €",
    "link": "/proizvod/boodles"
  },
  {
    "title": "BOSFORD ROSE",
    "price": "19,00 €",
    "link": "/proizvod/bosford-rose"
  },
  {
    "title": "BREWDOG LONEWOLF GIN",
    "price": "32,00 €",
    "link": "/proizvod/brewdog-lonewolf-gin"
  },
  {
    "title": "BROCKMAN'S",
    "price": "33,00 €",
    "link": "/proizvod/brockmans"
  },
  {
    "title": "BROCKMAN'S + ČAŠA",
    "price": "34,00 €",
    "link": "/proizvod/brockmans-casa"
  },
  {
    "title": "BROKER'S",
    "price": "17,00 €",
    "link": "/proizvod/brokers"
  },
  {
    "title": "BROOKLYN",
    "price": "50,00 €",
    "link": "/proizvod/brooklyn"
  },
  {
    "title": "BRUNSWICK GIN ACES DIAMONDS",
    "price": "39,00 €",
    "link": "/proizvod/brunswick-gin-aces-diamonds"
  },
  {
    "title": "BRUNSWICK GIN ACES HEARTS",
    "price": "39,00 €",
    "link": "/proizvod/brunswick-gin-aces-hearts"
  },
  {
    "title": "BRUNSWICK GIN ACES SPADES",
    "price": "39,00 €",
    "link": "/proizvod/brunswick-gin-aces-spades"
  },
  {
    "title": "BULLDOG",
    "price": "23,00 €",
    "link": "/proizvod/bulldog"
  },
  {
    "title": "CANNABIS SATIVA GIN",
    "price": "33,00 €",
    "link": "/proizvod/cannabis-sativa-gin"
  },
  {
    "title": "CAORUNN SMALL BATCH",
    "price": "29,00 €",
    "link": "/proizvod/caorunn-small-batch"
  },
  {
    "title": "CITADELLE",
    "price": "24,00 €",
    "link": "/proizvod/citadelle"
  },
  {
    "title": "COPPERHEAD BLACK BATCH",
    "price": "50,00 €",
    "link": "/proizvod/copperhead-black-batch"
  },
  {
    "title": "CRAFTER'S LONDON DRY GIN",
    "price": "27,00 €",
    "link": "/proizvod/crafters-london-dry-gin"
  },
  {
    "title": "CYRUS SAFFRON GIN",
    "price": "42,00 €",
    "link": "/proizvod/cyrus-saffron-gin"
  },
  {
    "title": "DICTADOR COLOMBIAN AGED BLACK",
    "price": "37,00 €",
    "link": "/proizvod/dictador-colombian-aged-black"
  },
  {
    "title": "DICTADOR COLOMBIAN AGED WHITE",
    "price": "41,00 €",
    "link": "/proizvod/dictador-colombian-aged-white"
  },
  {
    "title": "DRUMSHANBO GUNPOWDER",
    "price": "33,00 €",
    "link": "/proizvod/drumshanbo-gunpowder"
  },
  {
    "title": "DRUMSHANBO GUNPOWDER CALIFORNIAN ORANGE",
    "price": "37,00 €",
    "link": "/proizvod/drumshanbo-gunpowder-californian-orange"
  },
  {
    "title": "DRUMSHANBO GUNPOWDER KERAMIČKA BOCA",
    "price": "37,00 €",
    "link": "/proizvod/drumshanbo-gunpowder-keramicka-boca"
  },
  {
    "title": "EARL BROWN",
    "price": "7,00 €",
    "link": "/proizvod/earl-brown"
  },
  {
    "title": "EDEN MILL LOVE GIN",
    "price": "29,00 €",
    "link": "/proizvod/eden-mill-love-gin"
  },
  {
    "title": "EDEN MILL PASSION GIN",
    "price": "29,00 €",
    "link": "/proizvod/eden-mill-passion-gin"
  },
  {
    "title": "FIFTY POUNDS",
    "price": "29,00 €",
    "link": "/proizvod/fifty-pounds"
  },
  {
    "title": "G'VINE FLORAISON",
    "price": "44,00 €",
    "link": "/proizvod/gvine-floraison"
  },
  {
    "title": "GERANIUM",
    "price": "32,00 €",
    "link": "/proizvod/geranium"
  },
  {
    "title": "GIN LANE 1751 CLEMENTINE",
    "price": "20,00 €",
    "link": "/proizvod/gin-lane-1751-clementine"
  },
  {
    "title": "GIN LANE 1751 SLOE",
    "price": "20,00 €",
    "link": "/proizvod/gin-lane-1751-sloe"
  },
  {
    "title": "GIN LANE 1751 VICTORIA PINK",
    "price": "19,00 €",
    "link": "/proizvod/gin-lane-1751-victoria-pink"
  },
  {
    "title": "GINARTE FRIDA KAHLO",
    "price": "39,00 €",
    "link": "/proizvod/ginarte-frida-kahlo"
  },
  {
    "title": "GINATO CLEMENTINO GIN",
    "price": "25,00 €",
    "link": "/proizvod/ginato-clementino-gin"
  },
  {
    "title": "GINATO MELOGRANO GIN",
    "price": "25,00 €",
    "link": "/proizvod/ginato-melograno-gin"
  },
  {
    "title": "GINATO PINOT GRIGIO GIN",
    "price": "25,00 €",
    "link": "/proizvod/ginato-pinot-grigio-gin"
  },
  {
    "title": "GINATO POMPELMO GIN",
    "price": "25,00 €",
    "link": "/proizvod/ginato-pompelmo-gin"
  },
  {
    "title": "GOLD 999.9",
    "price": "35,00 €",
    "link": "/proizvod/gold-9999"
  },
  {
    "title": "GORDON'S",
    "price": "20,00 €",
    "link": "/proizvod/gordons"
  },
  {
    "title": "GORDONS'S PINK",
    "price": "18,00 €",
    "link": "/proizvod/gordonss-pink"
  },
  {
    "title": "HANAMI",
    "price": "28,00 €",
    "link": "/proizvod/hanami"
  },
  {
    "title": "HAPUSA HIMALAYAN DRY GIN",
    "price": "39,00 €",
    "link": "/proizvod/hapusa-himalayan-dry-gin"
  },
  {
    "title": "HARAHORN",
    "price": "29,00 €",
    "link": "/proizvod/harahorn"
  },
  {
    "title": "HAYMAN'S",
    "price": "26,00 €",
    "link": "/proizvod/haymans"
  },
  {
    "title": "HENDRICK'S",
    "price": "29,00 €",
    "link": "/proizvod/hendricks"
  },
  {
    "title": "HENDRICK'S NEPTUNIA",
    "price": "34,00 €",
    "link": "/proizvod/hendricks-neptunia"
  },
  {
    "title": "JAWBOX SMALL BATCH GIN",
    "price": "37,00 €",
    "link": "/proizvod/jawbox-small-batch-gin"
  },
  {
    "title": "JINZU",
    "price": "46,00 €",
    "link": "/proizvod/jinzu"
  },
  {
    "title": "KI NO BI KYOTO",
    "price": "51,00 €",
    "link": "/proizvod/ki-no-bi-kyoto"
  },
  {
    "title": "LIFE GUARD GIN",
    "price": "13,00 €",
    "link": "/proizvod/life-guard-gin"
  },
  {
    "title": "MALFY",
    "price": "25,00 €",
    "link": "/proizvod/malfy"
  },
  {
    "title": "MALFY GIN CON ARANCIA",
    "price": "27,00 €",
    "link": "/proizvod/malfy-gin-con-arancia"
  },
  {
    "title": "MARE",
    "price": "43,00 €",
    "link": "/proizvod/mare"
  },
  {
    "title": "MARE + LANTERNA",
    "price": "52,00 €",
    "link": "/proizvod/mare-lanterna"
  },
  {
    "title": "MARE CAPRI",
    "price": "60,00 €",
    "link": "/proizvod/mare-capri"
  },
  {
    "title": "MARE MAGNUM",
    "price": "109,00 €",
    "link": "/proizvod/mare-magnum"
  },
  {
    "title": "MARTIN MILLER'S",
    "price": "34,00 €",
    "link": "/proizvod/martin-millers"
  },
  {
    "title": "MONKEY 47",
    "price": "40,00 €",
    "link": "/proizvod/monkey-47"
  },
  {
    "title": "MONKEY 47 SLOE",
    "price": "50,00 €",
    "link": "/proizvod/monkey-47-sloe"
  },
  {
    "title": "NIKKA COFFEY GIN",
    "price": "39,00 €",
    "link": "/proizvod/nikka-coffey-gin"
  },
  {
    "title": "NORDES",
    "price": "30,00 €",
    "link": "/proizvod/nordes"
  },
  {
    "title": "OLD ENGLISH",
    "price": "37,00 €",
    "link": "/proizvod/old-english"
  },
  {
    "title": "PICKERING'S GIN",
    "price": "36,00 €",
    "link": "/proizvod/pickerings-gin"
  },
  {
    "title": "PICKERING'S GIN SCOTTISH BOTANICALS",
    "price": "36,00 €",
    "link": "/proizvod/pickerings-gin-scottish-botanicals"
  },
  {
    "title": "PINK 47",
    "price": "19,00 €",
    "link": "/proizvod/pink-47"
  },
  {
    "title": "PUERTO DE INDIAS STRAWBERRY",
    "price": "25,00 €",
    "link": "/proizvod/puerto-de-indias-strawberry"
  },
  {
    "title": "SCAPEGRACE BLACK",
    "price": "39,00 €",
    "link": "/proizvod/scapegrace-black"
  },
  {
    "title": "SCAPEGRACE CLASSIC",
    "price": "35,00 €",
    "link": "/proizvod/scapegrace-classic"
  },
  {
    "title": "SETTE MONTI",
    "price": "13,00 €",
    "link": "/proizvod/sette-monti"
  },
  {
    "title": "SIKKIM PRIVEE LONDON DRY GIN",
    "price": "27,00 €",
    "link": "/proizvod/sikkim-privee-london-dry-gin"
  },
  {
    "title": "SUL",
    "price": "34,00 €",
    "link": "/proizvod/sul"
  },
  {
    "title": "SUNTORY ROKU",
    "price": "29,00 €",
    "link": "/proizvod/suntory-roku"
  },
  {
    "title": "SUNTORY ROKU + 1 ČAŠA",
    "price": "31,00 €",
    "link": "/proizvod/suntory-roku-1-casa"
  },
  {
    "title": "TANGLIN SINGAPORE CRAFT GIN",
    "price": "39,00 €",
    "link": "/proizvod/tanglin-singapore-craft-gin"
  },
  {
    "title": "TANQUERAY",
    "price": "20,00 €",
    "link": "/proizvod/tanqueray"
  },
  {
    "title": "TANQUERAY BLACKCURRANT",
    "price": "29,00 €",
    "link": "/proizvod/tanqueray-blackcurrant"
  },
  {
    "title": "TANQUERAY FLOR DE SEVILLA",
    "price": "27,00 €",
    "link": "/proizvod/tanqueray-flor-de-sevilla"
  },
  {
    "title": "TANQUERAY RANGPUR",
    "price": "34,00 €",
    "link": "/proizvod/tanqueray-rangpur"
  },
  {
    "title": "TANQUERAY TEN",
    "price": "30,00 €",
    "link": "/proizvod/tanqueray-ten"
  },
  {
    "title": "THE BOTANIST",
    "price": "36,00 €",
    "link": "/proizvod/the-botanist"
  },
  {
    "title": "THE COPPER IN THE CLOUDS HERTFORDSHIRE GIN",
    "price": "45,00 €",
    "link": "/proizvod/the-copper-in-the-clouds-hertfordshire-gin"
  },
  {
    "title": "THE KING OF SOHO",
    "price": "29,00 €",
    "link": "/proizvod/the-king-of-soho"
  },
  {
    "title": "UNGAVA",
    "price": "29,00 €",
    "link": "/proizvod/ungava"
  },
  {
    "title": "WHITLEY NEILL CONNOISSEUR'S CUT GIN",
    "price": "24,00 €",
    "link": "/proizvod/whitley-neill-connoisseurs-cut-gin"
  },
  {
    "title": "WHITLEY NEILL ORIGINAL GIN",
    "price": "24,00 €",
    "link": "/proizvod/whitley-neill-original-gin"
  },
  {
    "title": "WHITLEY NEILL PARMA VIOLET GIN",
    "price": "24,00 €",
    "link": "/proizvod/whitley-neill-parma-violet-gin"
  },
  {
    "title": "WHITLEY NEILL RASPBERRY GIN",
    "price": "24,00 €",
    "link": "/proizvod/whitley-neill-raspberry-gin"
  },
  {
    "title": "XORIGUER MAHON CANET GIN",
    "price": "25,00 €",
    "link": "/proizvod/xoriguer-mahon-canet-gin"
  },
  {
    "title": "XORIGUER MAHON GIN",
    "price": "21,00 €",
    "link": "/proizvod/xoriguer-mahon-gin"
  }
]